[
    {
        "acronym": "CGT",
        "definition": "Cooking Gourmet Taste: A technique or style emphasizing rich, sophisticated flavors."
    },
    {
        "acronym": "FIT",
        "definition": "Fast, Innovative, Tasty: A method of cooking focused on quick, creative, and delicious meals."
    },
    {
        "acronym": "HPS",
        "definition": "Herbs, Pasta, Spices: A cooking approach that heavily incorporates herbs and spices with pasta dishes."
    },
    {
        "acronym": "MBC",
        "definition": "Maximize Bite Crunch: A how-to about achieving the crunchiest and most satisfying texture in dishes."
    },
    {
        "acronym": "PGC",
        "definition": "Perfectly Gourmet Cooking: Striving for refined and luxurious cooking standards in recipes."
    },
    {
        "acronym": "RMN",
        "definition": "Rotate Meal Nights, often used in planning weekly mealtimes or suggesting a method for varied dishes."
    },
    {
        "acronym": "SCM",
        "definition": "Seasonal Culinary Mix: A cooking trend focusing on seasonal ingredients to enhance freshness and flavor."
    },
    {
        "acronym": "TFC",
        "definition": "The Flavor Factory Cooking: A technique that emphasizes enhancing and layering flavors in every dish."
    },
    {
        "acronym": "PECB",
        "definition": "Plant-Exclusive Cooking Bench: A diet-restricting trend that focuses on plant-only meals."
    },
    {
        "acronym": "RICH",
        "definition": "Really Intensified Culinary Hacks, Tips and tricks to enhance the dish more effectively all round."
    }
]